ngram_polars-0.1.1.dist-info/METADATA
ngram_polars-0.1.1.dist-info/WHEEL
ngram_polars-0.1.1.dist-info/licenses/LICENSE
ngram_polars/__init__.py
ngram_polars/__pycache__/__init__.cpython-312.pyc
ngram_polars/ngram_polars.cpython-310-x86_64-linux-gnu.so
ngram_polars-0.1.1.dist-info/RECORD
