Metadata-Version: 2.4
Name: ngram_polars
Version: 0.1.1
Classifier: Programming Language :: Rust
Classifier: Programming Language :: Python :: Implementation :: CPython
Classifier: Programming Language :: Python :: Implementation :: PyPy
Classifier: Development Status :: 4 - Beta
Classifier: Intended Audience :: Developers
Classifier: Intended Audience :: Science/Research
Classifier: License :: OSI Approved :: MIT License
Classifier: Operating System :: OS Independent
Classifier: Programming Language :: Python :: 3
Classifier: Programming Language :: Python :: 3.9
Classifier: Programming Language :: Python :: 3.10
Classifier: Programming Language :: Python :: 3.11
Classifier: Programming Language :: Python :: 3.12
Classifier: Programming Language :: Python :: 3.13
Classifier: Topic :: Scientific/Engineering :: Information Analysis
Classifier: Topic :: Text Processing :: Linguistic
Classifier: Topic :: Software Development :: Libraries :: Python Modules
Requires-Dist: pytest ; extra == 'dev'
Requires-Dist: pytest-benchmark ; extra == 'dev'
Provides-Extra: dev
License-File: LICENSE
Summary: High-performance n-gram generation for Polars
Keywords: ngram,polars,text-processing,nlp,data-analysis
Author: Eric
License: MIT
Requires-Python: >=3.9
Project-URL: Homepage, https://github.com/ericqu/ngram-rs/tree/main/ngram_polars
Project-URL: Repository, https://github.com/ericqu/ngram-rs/tree/main/ngram_polars
Project-URL: Bug Tracker, https://github.com/ericqu/ngram-rs/issues
